setup.cfg
setup.py
pyunderscore.egg-info/PKG-INFO
pyunderscore.egg-info/SOURCES.txt
pyunderscore.egg-info/dependency_links.txt
pyunderscore.egg-info/top_level.txt
tests/__init__.py
tests/helpers.py
tests/test_arrays.py
tests/test_collections.py
underscore/__init__.py
underscore/array.py
underscore/collection.py